oneNeuron/__init__.py
oneNeuron/perceptron.py
OneNeuronPerceptron_pypi_CodinjaoftheWorld-0.0.1.dist-info/LICENSE
OneNeuronPerceptron_pypi_CodinjaoftheWorld-0.0.1.dist-info/METADATA
OneNeuronPerceptron_pypi_CodinjaoftheWorld-0.0.1.dist-info/WHEEL
OneNeuronPerceptron_pypi_CodinjaoftheWorld-0.0.1.dist-info/top_level.txt
OneNeuronPerceptron_pypi_CodinjaoftheWorld-0.0.1.dist-info/RECORD
