Metadata-Version: 2.1
Name: OneNeuronPerceptron-pypi-CodinjaoftheWorld
Version: 0.0.1
Summary: Implementation of Perceptron
Home-page: https://github.com/CodinjaoftheWorld/OneNeuronPerceptron_pypi
Author: CodinjaoftheWorld
Author-email: gauravsaini.728@gmail.com
License: UNKNOWN
Project-URL: Bug Tracker, https://github.com/CodinjaoftheWorld/OneNeuronPerceptron_pypi/issues
Platform: UNKNOWN
Classifier: Programming Language :: Python :: 3
Classifier: License :: OSI Approved :: MIT License
Classifier: Operating System :: OS Independent
Requires-Python: >=3.6
License-File: LICENSE
Requires-Dist: numpy
Requires-Dist: tqdm
